outlier_hub/__init__.py
outlier_hub/datasets/__init__.py
outlier_hub/datasets/arrhythmia/__init__.py
outlier_hub/datasets/arrhythmia/factory.py
outlier_hub/datasets/arrhythmia/iterator.py
outlier_hub/datasets/arrhythmia/preprocessor.py
outlier_hub/datasets/atis/__init__.py
outlier_hub/datasets/atis/factory.py
outlier_hub/datasets/atis/iterator.py
outlier_hub/datasets/atis/preprocessor.py
outlier_hub/datasets/emnist/__init__.py
outlier_hub/datasets/emnist/factory.py
outlier_hub/datasets/emnist/iterator.py
outlier_hub/datasets/emnist/preprocessor.py
outlier_hub/datasets/fashion_mnist/__init__.py
outlier_hub/datasets/fashion_mnist/factory.py
outlier_hub/datasets/fashion_mnist/iterator.py
outlier_hub/datasets/fashion_mnist/preprocessor.py
outlier_hub/datasets/ham10k/__init__.py
outlier_hub/datasets/ham10k/factory.py
outlier_hub/datasets/ham10k/iterator.py
outlier_hub/datasets/ham10k/preprocessor.py
outlier_hub/datasets/kdd/__init__.py
outlier_hub/datasets/kdd/factory.py
outlier_hub/datasets/kdd/iterator.py
outlier_hub/datasets/kdd/preprocessor.py
outlier_hub/datasets/newsgroups/__init__.py
outlier_hub/datasets/newsgroups/factory.py
outlier_hub/datasets/newsgroups/iterator.py
outlier_hub/datasets/newsgroups/preprocessor.py
outlier_hub/datasets/reuters/__init__.py
outlier_hub/datasets/reuters/factory.py
outlier_hub/datasets/reuters/iterator.py
outlier_hub/datasets/reuters/preprocessor.py
outlier_hub/datasets/toy_datasets/__init__.py
outlier_hub/datasets/toy_datasets/circles/__init__.py
outlier_hub/datasets/toy_datasets/circles/factory.py
outlier_hub/datasets/toy_datasets/circles/iterator.py
outlier_hub/datasets/toy_datasets/circular_segment/__init__.py
outlier_hub/datasets/toy_datasets/circular_segment/factory.py
outlier_hub/datasets/toy_datasets/circular_segment/iterator.py
outlier_hub/datasets/toy_datasets/gaussian/__init__.py
outlier_hub/datasets/toy_datasets/gaussian/factory.py
outlier_hub/datasets/toy_datasets/gaussian/iterator.py
outlier_hub-0.0.13.dist-info/METADATA
outlier_hub-0.0.13.dist-info/WHEEL
outlier_hub-0.0.13.dist-info/top_level.txt
outlier_hub-0.0.13.dist-info/RECORD
