Metadata-Version: 2.1
Name: outlier-hub
Version: 0.0.13
Summary: Outlierhub, a collection of machine learning datasets.
Home-page: UNKNOWN
Author: Max Luebbering, Rajkumar Ramamurthy, Michael Gebauer
License: UNKNOWN
Platform: UNKNOWN
Requires-Python: >=3.7
Requires-Dist: nltk
Requires-Dist: datastack
Requires-Dist: pandas
Requires-Dist: h5py
Requires-Dist: torch
Requires-Dist: tqdm
Requires-Dist: flair
Requires-Dist: torchtext
